nmrbox_slack/__init__.py
nmrbox_slack/slacklogger.py
slack_webclient_logger-2.2.2.dist-info/LICENSE
slack_webclient_logger-2.2.2.dist-info/METADATA
slack_webclient_logger-2.2.2.dist-info/WHEEL
slack_webclient_logger-2.2.2.dist-info/top_level.txt
slack_webclient_logger-2.2.2.dist-info/RECORD
