Metadata-Version: 2.1
Name: slack-webclient-logger
Version: 2.2.2
Summary: Python logging handler which posts to slack
Home-page: https://github.com/NMRbox/slacklogger
Author: Gerard Weatherby
Author-email: gweatherby@uchc.edu
Keywords: slack logger
Classifier: Programming Language :: Python :: 3
Classifier: License :: OSI Approved :: MIT License
Classifier: Operating System :: OS Independent
Requires-Python: >=3.7
License-File: LICENSE
Requires-Dist: slackclient (>=2.5.0)
